prg2tap/__init__.py
prg2tap/prg2tap.py
prg2tap/test/__init__.py
prg2tap/test/test_prg2tap.py
prg2tap-0.0.3.data/scripts/prg2tap
prg2tap-0.0.3.dist-info/LICENSE
prg2tap-0.0.3.dist-info/METADATA
prg2tap-0.0.3.dist-info/WHEEL
prg2tap-0.0.3.dist-info/top_level.txt
prg2tap-0.0.3.dist-info/RECORD
