Metadata-Version: 2.1
Name: prg2tap
Version: 0.0.3
Summary: Convert KickAssembler prg object code to Oric tap file
Home-page: https://github.com/peckhamdata/prg2tap
Author: worldofchris
Author-email: chris@worldofchris.com
License: MIT
Platform: UNKNOWN
Classifier: Programming Language :: Python :: 3
Classifier: License :: OSI Approved :: MIT License
Classifier: Operating System :: OS Independent
Requires-Python: >=3.6
Requires-Dist: pytest
